{
  "version": "5",
  "dialect": "mysql",
  "id": "dc8883b4-2c1a-410d-adac-ce53ea630184",
  "prevId": "621b4c1a-153f-4a91-912a-ad177687aeb6",
  "tables": {
    "coin_readings": {
      "name": "coin_readings",
      "columns": {
        "id": {
          "name": "id",
          "type": "int",
          "primaryKey": false,
          "notNull": true,
          "autoincrement": true
        },
        "deviceId": {
          "name": "deviceId",
          "type": "int",
          "primaryKey": false,
          "notNull": false,
          "autoincrement": false
        },
        "coinResults": {
          "name": "coinResults",
          "type": "json",
          "primaryKey": false,
          "notNull": true,
          "autoincrement": false
        },
        "analysis": {
          "name": "analysis",
          "type": "json",
          "primaryKey": false,
          "notNull": false,
          "autoincrement": false
        },
        "tossDate": {
          "name": "tossDate",
          "type": "date",
          "primaryKey": false,
          "notNull": true,
          "autoincrement": false
        },
        "type": {
          "name": "type",
          "type": "varchar(50)",
          "primaryKey": false,
          "notNull": true,
          "autoincrement": false,
          "default": "'daily_fortune'"
        },
        "createdAt": {
          "name": "createdAt",
          "type": "timestamp",
          "primaryKey": false,
          "notNull": true,
          "autoincrement": false,
          "default": "(now())"
        },
        "updatedAt": {
          "name": "updatedAt",
          "type": "timestamp",
          "primaryKey": false,
          "notNull": true,
          "autoincrement": false,
          "onUpdate": true,
          "default": "(now())"
        }
      },
      "indexes": {},
      "foreignKeys": {},
      "compositePrimaryKeys": {
        "coin_readings_id": {
          "name": "coin_readings_id",
          "columns": [
            "id"
          ]
        }
      },
      "uniqueConstraints": {},
      "checkConstraint": {}
    },
    "devices": {
      "name": "devices",
      "columns": {
        "id": {
          "name": "id",
          "type": "int",
          "primaryKey": false,
          "notNull": true,
          "autoincrement": true
        },
        "deviceFingerprint": {
          "name": "deviceFingerprint",
          "type": "varchar(255)",
          "primaryKey": false,
          "notNull": true,
          "autoincrement": false
        },
        "lastTossDate": {
          "name": "lastTossDate",
          "type": "date",
          "primaryKey": false,
          "notNull": false,
          "autoincrement": false
        },
        "lastReadingId": {
          "name": "lastReadingId",
          "type": "int",
          "primaryKey": false,
          "notNull": false,
          "autoincrement": false
        },
        "createdAt": {
          "name": "createdAt",
          "type": "timestamp",
          "primaryKey": false,
          "notNull": true,
          "autoincrement": false,
          "default": "(now())"
        },
        "updatedAt": {
          "name": "updatedAt",
          "type": "timestamp",
          "primaryKey": false,
          "notNull": true,
          "autoincrement": false,
          "onUpdate": true,
          "default": "(now())"
        }
      },
      "indexes": {},
      "foreignKeys": {},
      "compositePrimaryKeys": {
        "devices_id": {
          "name": "devices_id",
          "columns": [
            "id"
          ]
        }
      },
      "uniqueConstraints": {
        "devices_deviceFingerprint_unique": {
          "name": "devices_deviceFingerprint_unique",
          "columns": [
            "deviceFingerprint"
          ]
        }
      },
      "checkConstraint": {}
    }
  },
  "views": {},
  "_meta": {
    "schemas": {},
    "tables": {},
    "columns": {}
  },
  "internal": {
    "tables": {},
    "indexes": {}
  }
}